Metadata-Version: 2.1
Name: pyperstream
Version: 0.1
Summary: A small simple Stream API-like wrapper.
Home-page: https://github.com/IlyasYOY/python-streamer
Author: Ilia Ilinykh
Author-email: ilyasyoy@gmail.com
License: UNKNOWN
Platform: UNKNOWN
